{
  "fixes_applied": [
    {
      "fix": "redis_operations",
      "status": "success",
      "details": "Fixed Redis set/get operations with proper encoding"
    },
    {
      "fix": "unified_kb_endpoint",
      "status": "success",
      "working_endpoint": "/",
      "details": "Found working endpoint: /"
    },
    {
      "fix": "cache_integration",
      "status": "failed",
      "error": "list index out of range"
    },
    {
      "fix": "chat_optimization",
      "status": "acceptable",
      "avg_time_ms": 588.8729095458984,
      "min_time_ms": 373.1536865234375,
      "max_time_ms": 908.5898399353027,
      "optimization_needed": false,
      "details": "Chat response time analysis: acceptable"
    }
  ],
  "test_results": {
    "validation": {
      "redis": {
        "working": true,
        "details": "Redis operations working correctly"
      },
      "agent_selector": {
        "working": false,
        "error": "list index out of range"
      },
      "main_api": {
        "working": true,
        "response_time_ms": 1035.1922512054443,
        "status_code": 200,
        "details": "Main API working correctly"
      }
    }
  }
}